ida_settings/__init__.py
ida_settings/legacy.py
ida_settings/py.typed
ida_settings-3.2.2.dist-info/WHEEL
ida_settings-3.2.2.dist-info/METADATA
ida_settings-3.2.2.dist-info/RECORD
