Metadata-Version: 2.3
Name: ida-settings
Version: 3.2.2
Summary: Fetch configuration values for IDA Pro plugins
Author: Willi Ballenthin
Author-email: Willi Ballenthin <wballenthin@hex-rays.com>
Requires-Dist: ida-hcli>=0.12.1
Requires-Python: >=3.10
